synthetic_data/__init__.py
synthetic_data/base_generator.py
synthetic_data/generator_builder.py
synthetic_data/generators.py
synthetic_data/graph_synthetic_data.py
synthetic_data/marginal_dist.py
synthetic_data/null_replication.py
synthetic_data/parser.py
synthetic_data/synthetic_data.py
synthetic_data/utils.py
synthetic_data/distinct_generators/__init__.py
synthetic_data/distinct_generators/categorical_generator.py
synthetic_data/distinct_generators/datetime_generator.py
synthetic_data/distinct_generators/float_generator.py
synthetic_data/distinct_generators/int_generator.py
synthetic_data/distinct_generators/null_generator.py
synthetic_data/distinct_generators/text_generator.py
synthetic_data-1.2.3.dist-info/LICENSE
synthetic_data-1.2.3.dist-info/METADATA
synthetic_data-1.2.3.dist-info/WHEEL
synthetic_data-1.2.3.dist-info/top_level.txt
synthetic_data-1.2.3.dist-info/RECORD
