Metadata-Version: 2.1
Name: synthetic-data
Version: 1.2.3
Summary: Generates complex, nonlinear datasets for use         with deep learning/black box models
Home-page: https://github.com/capitalone/synthetic-data
Maintainer: Brian Barr
Maintainer-email: brian.barr@capitalone.com
License: Apache License 2.0
Requires-Python: >=3.8
License-File: LICENSE
Requires-Dist: numpy >=1.22.0
Requires-Dist: scikit-learn >=1.1.0
Requires-Dist: scipy >=1.10.0
Requires-Dist: dataprofiler >=0.10.3
